{
  "$schema": "https://developer.microsoft.com/json-schemas/fabric/item/report/definition/visualContainer/2.2.0/schema.json",
  "name": "380eb7bd4c07031336c3",
  "position": {
    "x": 0,
    "y": 92.401215805471125,
    "z": 0,
    "height": 627.355623100304,
    "width": 1280
  },
  "visual": {
    "visualType": "pivotTable",
    "query": {
      "queryState": {
        "Columns": {
          "projections": [
            {
              "field": {
                "Column": {
                  "Expression": {
                    "SourceRef": {
                      "Entity": "Severity"
                    }
                  },
                  "Property": "Severity"
                }
              },
              "queryRef": "Severity.Severity",
              "active": true
            }
          ]
        },
        "Rows": {
          "projections": [
            {
              "field": {
                "Column": {
                  "Expression": {
                    "SourceRef": {
                      "Entity": "Root Cause Analysis Type"
                    }
                  },
                  "Property": "Root Cause Analysis Type"
                }
              },
              "queryRef": "Root Cause Analysis Type.Root Cause Analysis Type",
              "active": true
            },
            {
              "field": {
                "Column": {
                  "Expression": {
                    "SourceRef": {
                      "Entity": "Root Cause Analysis Fact"
                    }
                  },
                  "Property": "Root Cause Analysis"
                }
              },
              "queryRef": "Root Cause Analysis Fact.Root Cause Analysis",
              "active": true
            }
          ]
        },
        "Values": {
          "projections": [
            {
              "field": {
                "Aggregation": {
                  "Expression": {
                    "Column": {
                      "Expression": {
                        "SourceRef": {
                          "Entity": "Issue"
                        }
                      },
                      "Property": "Issue Count"
                    }
                  },
                  "Function": 0
                }
              },
              "queryRef": "Sum(Issue.Issue Count)"
            }
          ]
        }
      }
    },
    "expansionStates": [
      {
        "roles": [
          "Rows"
        ],
        "levels": [
          {
            "queryRefs": [
              "Root Cause Analysis Type.Root Cause Analysis Type"
            ],
            "isPinned": true
          },
          {
            "queryRefs": [
              "Root Cause Analysis Fact.Root Cause Analysis"
            ],
            "isCollapsed": true,
            "isPinned": true
          }
        ],
        "root": {}
      }
    ],
    "objects": {
      "subTotals": [
        {
          "properties": {
            "columnSubtotals": {
              "expr": {
                "Literal": {
                  "Value": "false"
                }
              }
            },
            "rowSubtotals": {
              "expr": {
                "Literal": {
                  "Value": "false"
                }
              }
            },
            "perRowLevel": {
              "expr": {
                "Literal": {
                  "Value": "false"
                }
              }
            },
            "rowSubtotalsLabel": {
              "expr": {
                "Literal": {
                  "Value": "'out of a total number of issues'"
                }
              }
            }
          }
        }
      ],
      "columnWidth": [
        {
          "properties": {
            "value": {
              "expr": {
                "Literal": {
                  "Value": "39D"
                }
              }
            }
          },
          "selector": {
            "data": [
              {
                "scopeId": {
                  "Comparison": {
                    "ComparisonKind": 0,
                    "Left": {
                      "Column": {
                        "Expression": {
                          "SourceRef": {
                            "Entity": "Severity"
                          }
                        },
                        "Property": "Severity"
                      }
                    },
                    "Right": {
                      "Literal": {
                        "Value": "'High'"
                      }
                    }
                  }
                }
              }
            ]
          }
        },
        {
          "properties": {
            "value": {
              "expr": {
                "Literal": {
                  "Value": "332.157428748544D"
                }
              }
            }
          },
          "selector": {
            "metadata": "Root Cause Analysis Type.Root Cause Analysis Type"
          }
        },
        {
          "properties": {
            "value": {
              "expr": {
                "Literal": {
                  "Value": "61D"
                }
              }
            }
          },
          "selector": {
            "data": [
              {
                "scopeId": {
                  "Comparison": {
                    "ComparisonKind": 0,
                    "Left": {
                      "Column": {
                        "Expression": {
                          "SourceRef": {
                            "Entity": "Severity"
                          }
                        },
                        "Property": "Severity"
                      }
                    },
                    "Right": {
                      "Literal": {
                        "Value": "'Medium'"
                      }
                    }
                  }
                }
              }
            ]
          }
        },
        {
          "properties": {
            "value": {
              "expr": {
                "Literal": {
                  "Value": "51D"
                }
              }
            }
          },
          "selector": {
            "data": [
              {
                "scopeId": {
                  "Comparison": {
                    "ComparisonKind": 0,
                    "Left": {
                      "Column": {
                        "Expression": {
                          "SourceRef": {
                            "Entity": "Severity"
                          }
                        },
                        "Property": "Severity"
                      }
                    },
                    "Right": {
                      "Literal": {
                        "Value": "'Critical'"
                      }
                    }
                  }
                }
              }
            ]
          }
        },
        {
          "properties": {
            "value": {
              "expr": {
                "Literal": {
                  "Value": "36D"
                }
              }
            }
          },
          "selector": {
            "data": [
              {
                "scopeId": {
                  "Comparison": {
                    "ComparisonKind": 0,
                    "Left": {
                      "Column": {
                        "Expression": {
                          "SourceRef": {
                            "Entity": "Severity"
                          }
                        },
                        "Property": "Severity"
                      }
                    },
                    "Right": {
                      "Literal": {
                        "Value": "'Low'"
                      }
                    }
                  }
                }
              }
            ]
          }
        }
      ]
    },
    "drillFilterOtherVisuals": true
  }
}